{
  "Object": "PricebookEntry",
  "Fields": {
    "GearsetDisplayName": "Standard Price Book - Desktop Computer",
    "GearsetExternalId__c": "YAYRT64000000TWu10",
    "IsActive": "true",
    "UnitPrice": "700.0",
    "UseStandardPrice": "false"
  },
  "References": [
    {
      "Name": "Pricebook2",
      "ReferencedObject": "Pricebook2",
      "ReferencedFields": {
        "GearsetExternalId__c": "StandardPriceBook"
      }
    },
    {
      "Name": "Product2",
      "ReferencedObject": "Product2",
      "ReferencedFields": {
        "GearsetExternalId__c": "YAYTOo3100000TWt10"
      }
    }
  ]
}